minitroncontrol/__init__.py
minitroncontrol/rover.py
MINITRONCONTROL-0.1.0.dist-info/METADATA
MINITRONCONTROL-0.1.0.dist-info/WHEEL
MINITRONCONTROL-0.1.0.dist-info/top_level.txt
MINITRONCONTROL-0.1.0.dist-info/RECORD
