Metadata-Version: 2.1
Name: MINITRONCONTROL
Version: 0.1.0
Summary: A Python library to control a four-wheel rover via HTTP requests
Author: Your Name
Author-email: your.email@example.com
Classifier: Programming Language :: Python :: 3
Classifier: License :: OSI Approved :: MIT License
Classifier: Operating System :: OS Independent
Requires-Python: >=3.6
Requires-Dist: requests
